{
    "aggregations_about": "/aggregation/provider/534/490f3209_3056_4a36_a917_972f486fdaa8",
    "webResources": [
        {
            "about": "https://images.memorix.nl/bru/thumb/1000x1000/2e672940-126a-4c17-bb57-173be764ba11.jpg",
            "textAttributionSnippet": "(nl) Zicht op de toegangspoort van het Prinselijk Begijnhof De Wijngaard - https://www.europeana.eu/item/534/490f3209_3056_4a36_a917_972f486fdaa8. (nl) Sugg (Gent). (nl) Stadsarchief Brugge - https://www.beeldbankbrugge.be. Public Domain Mark - http://creativecommons.org/publicdomain/mark/1.0/",
            "htmlAttributionSnippet": "<link rel='stylesheet' type='text/css' href='https://api.europeana.eu/attribution/style.css'/><dl class='europeana-attribution' lang='en'><dt>Title</dt><dd lang='nl'><a href='http://data.europeana.eu/item/534/490f3209_3056_4a36_a917_972f486fdaa8' target='_blank' rel='noopener'>Zicht op de toegangspoort van het Prinselijk Begijnhof De Wijngaard</a></dd><dt>Creator</dt><dd lang='nl'>Sugg (Gent)</dd><dt>Institution</dt><dd lang='nl'><a href='https://www.beeldbankbrugge.be' target='_blank' rel='noopener'>Stadsarchief Brugge</a></dd><dt>Country</dt><dd lang=''>Belgium</dd><dt>Rights</dt><dd><a href='http://creativecommons.org/publicdomain/mark/1.0/' target='_blank' rel='noopener'><span class='icon-pd'/>Public Domain Mark</a></dd></dl>",
            "dctermsIsReferencedBy": [
                "https://iiif.europeana.eu/presentation/534/490f3209_3056_4a36_a917_972f486fdaa8/manifest"
            ],
            "ebucoreHasMimeType": "image/jpeg",
            "ebucoreFileByteSize": 149001,
            "ebucoreWidth": 1000,
            "ebucoreHeight": 653,
            "edmHasColorSpace": "sRGB",
            "edmComponentColor": [
                "#EEE8AA",
                "#A9A9A9",
                "#F5DEB3",
                "#8FBC8F",
                "#BDB76B",
                "#000000"
            ],
            "ebucoreOrientation": "landscape"
        },
        {
            "about": "https://www.beeldbankbrugge.be",
            "textAttributionSnippet": "(nl) Zicht op de toegangspoort van het Prinselijk Begijnhof De Wijngaard - https://www.europeana.eu/item/534/490f3209_3056_4a36_a917_972f486fdaa8. (nl) Sugg (Gent). (nl) Stadsarchief Brugge - https://www.beeldbankbrugge.be. Public Domain Mark - http://creativecommons.org/publicdomain/mark/1.0/",
            "htmlAttributionSnippet": "<link rel='stylesheet' type='text/css' href='https://api.europeana.eu/attribution/style.css'/><dl class='europeana-attribution' lang='en'><dt>Title</dt><dd lang='nl'><a href='http://data.europeana.eu/item/534/490f3209_3056_4a36_a917_972f486fdaa8' target='_blank' rel='noopener'>Zicht op de toegangspoort van het Prinselijk Begijnhof De Wijngaard</a></dd><dt>Creator</dt><dd lang='nl'>Sugg (Gent)</dd><dt>Institution</dt><dd lang='nl'><a href='https://www.beeldbankbrugge.be' target='_blank' rel='noopener'>Stadsarchief Brugge</a></dd><dt>Country</dt><dd lang=''>Belgium</dd><dt>Rights</dt><dd><a href='http://creativecommons.org/publicdomain/mark/1.0/' target='_blank' rel='noopener'><span class='icon-pd'/>Public Domain Mark</a></dd></dl>",
            "ebucoreHasMimeType": "text/html",
            "ebucoreFileByteSize": 0
        },
        {
            "about": "https://iiif.europeana.eu/presentation/534/490f3209_3056_4a36_a917_972f486fdaa8/manifest",
            "rdfType": "http://iiif.io/api/presentation/3#Manifest"
        }
    ],
    "concept_label": [
        "picture postcards"
    ],
    "concept_note": [
        "Postcards having a pictorial image on one side, often representations of a place or works of art, upon which a message can be written, then posted."
    ],
    "edmDatasetName": [
        "534_Photoconsortium_Brugge"
    ],
    "edmCountry": [
        "Belgium"
    ],
    "edmLanguage": [
        "nl"
    ],
    "organization_label": [
        "PHOTOCONSORTIUM"
    ],
    "coordinate": [
        [
            51.25,
            3.21667
        ],
        [
            51.20892,
            3.22424
        ]
    ]
}