{
    "aggregations_about": "/aggregation/provider/951/Culturalia_5cdb6f57_9cfe_4ad9_a714_14cc5d140873",
    "webResources": [
        {
            "about": "https://culturalia.ro/entities/5cdb6f57-9cfe-4ad9-a714-14cc5d140873/view",
            "textAttributionSnippet": " - https://www.europeana.eu/item/951/Culturalia_5cdb6f57_9cfe_4ad9_a714_14cc5d140873. Editura Libr\u0103riei Ioan Laz\u0103r. Muzeul Na\u021bional Brukenthal - https://culturalia.ro/entities/5cdb6f57-9cfe-4ad9-a714-14cc5d140873/view. CC BY-SA - http://creativecommons.org/licenses/by-sa/4.0/",
            "htmlAttributionSnippet": "<link rel='stylesheet' type='text/css' href='https://api.europeana.eu/attribution/style.css'/><dl class='europeana-attribution' lang='en'><dt>Creator</dt><dd lang=''>Editura Libr\u0103riei Ioan Laz\u0103r</dd><dt>Institution</dt><dd lang=''><a href='https://culturalia.ro/entities/5cdb6f57-9cfe-4ad9-a714-14cc5d140873/view' target='_blank' rel='noopener'>Muzeul Na\u021bional Brukenthal</a></dd><dt>Country</dt><dd lang=''>Romania</dd><dt>Rights</dt><dd><a href='http://creativecommons.org/licenses/by-sa/4.0/' target='_blank' rel='noopener'><span class='icon-cc'/><span class='icon-by'/><span class='icon-sa'/>CC BY-SA</a></dd></dl>",
            "ebucoreHasMimeType": "text/html",
            "ebucoreFileByteSize": 0
        },
        {
            "about": "https://resource.culturalia.ro/public/2000/01/01/_SB-BRUK-validat_08%20august%202020_istorie_voina_docpatv494/Imagini1/E1E369D073F64FFAA999F6CBAFC4EFFB.tif",
            "textAttributionSnippet": " - https://www.europeana.eu/item/951/Culturalia_5cdb6f57_9cfe_4ad9_a714_14cc5d140873. Editura Libr\u0103riei Ioan Laz\u0103r. Muzeul Na\u021bional Brukenthal - https://culturalia.ro/entities/5cdb6f57-9cfe-4ad9-a714-14cc5d140873/view. CC BY-SA - http://creativecommons.org/licenses/by-sa/4.0/",
            "htmlAttributionSnippet": "<link rel='stylesheet' type='text/css' href='https://api.europeana.eu/attribution/style.css'/><dl class='europeana-attribution' lang='en'><dt>Creator</dt><dd lang=''>Editura Libr\u0103riei Ioan Laz\u0103r</dd><dt>Institution</dt><dd lang=''><a href='https://culturalia.ro/entities/5cdb6f57-9cfe-4ad9-a714-14cc5d140873/view' target='_blank' rel='noopener'>Muzeul Na\u021bional Brukenthal</a></dd><dt>Country</dt><dd lang=''>Romania</dd><dt>Rights</dt><dd><a href='http://creativecommons.org/licenses/by-sa/4.0/' target='_blank' rel='noopener'><span class='icon-cc'/><span class='icon-by'/><span class='icon-sa'/>CC BY-SA</a></dd></dl>",
            "dctermsIsReferencedBy": [
                "https://iiif.europeana.eu/presentation/951/Culturalia_5cdb6f57_9cfe_4ad9_a714_14cc5d140873/manifest"
            ],
            "ebucoreHasMimeType": "image/tiff",
            "ebucoreFileByteSize": 21755452,
            "ebucoreWidth": 3413,
            "ebucoreHeight": 2123,
            "edmHasColorSpace": "sRGB",
            "edmComponentColor": [
                "#A9A9A9",
                "#DCDCDC",
                "#FFE4C4",
                "#FAEBD7",
                "#EEE8AA",
                "#F5DEB3"
            ],
            "ebucoreOrientation": "landscape"
        },
        {
            "about": "https://resource.culturalia.ro/public/2000/01/01/_SB-BRUK-validat_08%20august%202020_istorie_voina_docpatv494/Imagini1/5F4A2BC7F0AC4C7195B595EDFD8E3AAD.tif",
            "textAttributionSnippet": " - https://www.europeana.eu/item/951/Culturalia_5cdb6f57_9cfe_4ad9_a714_14cc5d140873. Editura Libr\u0103riei Ioan Laz\u0103r. Muzeul Na\u021bional Brukenthal - https://culturalia.ro/entities/5cdb6f57-9cfe-4ad9-a714-14cc5d140873/view. CC BY-SA - http://creativecommons.org/licenses/by-sa/4.0/",
            "htmlAttributionSnippet": "<link rel='stylesheet' type='text/css' href='https://api.europeana.eu/attribution/style.css'/><dl class='europeana-attribution' lang='en'><dt>Creator</dt><dd lang=''>Editura Libr\u0103riei Ioan Laz\u0103r</dd><dt>Institution</dt><dd lang=''><a href='https://culturalia.ro/entities/5cdb6f57-9cfe-4ad9-a714-14cc5d140873/view' target='_blank' rel='noopener'>Muzeul Na\u021bional Brukenthal</a></dd><dt>Country</dt><dd lang=''>Romania</dd><dt>Rights</dt><dd><a href='http://creativecommons.org/licenses/by-sa/4.0/' target='_blank' rel='noopener'><span class='icon-cc'/><span class='icon-by'/><span class='icon-sa'/>CC BY-SA</a></dd></dl>",
            "dctermsIsReferencedBy": [
                "https://iiif.europeana.eu/presentation/951/Culturalia_5cdb6f57_9cfe_4ad9_a714_14cc5d140873/manifest"
            ],
            "ebucoreHasMimeType": "image/tiff",
            "ebucoreFileByteSize": 21755452,
            "ebucoreWidth": 3413,
            "ebucoreHeight": 2123,
            "edmHasColorSpace": "sRGB",
            "edmComponentColor": [
                "#808080",
                "#F5DEB3",
                "#FAEBD7",
                "#2F4F4F",
                "#A9A9A9",
                "#FFE4C4"
            ],
            "ebucoreOrientation": "landscape"
        },
        {
            "about": "https://iiif.europeana.eu/presentation/951/Culturalia_5cdb6f57_9cfe_4ad9_a714_14cc5d140873/manifest",
            "rdfType": "http://iiif.io/api/presentation/3#Manifest"
        }
    ],
    "concept_label": [
        "Postcard"
    ],
    "concept_note": [
        "Type of postal stationery"
    ],
    "edmDatasetName": [
        "951_Ministerul_Culturii_Artifacts"
    ],
    "edmCountry": [
        "Romania"
    ],
    "edmLanguage": [
        "ro"
    ],
    "organization_label": [
        "National Heritage Institute, Bucharest"
    ],
    "coordinate": [
        [
            46.0,
            25.0
        ],
        [
            45.8333,
            24.9833
        ],
        [
            45.87,
            24.23
        ],
        [
            46.0,
            25.0
        ],
        [
            45.7667,
            24.15
        ]
    ]
}