{
    "aggregations_about": "/aggregation/provider/951/Culturalia_67b766b9_c5d3_47ec_8286_2f7e734b45ca",
    "webResources": [
        {
            "about": "https://culturalia.ro/entities/67b766b9-c5d3-47ec-8286-2f7e734b45ca/view",
            "textAttributionSnippet": " - https://www.europeana.eu/item/951/Culturalia_67b766b9_c5d3_47ec_8286_2f7e734b45ca. Editura Schwarze, Bra\u0219ov (\u0219i fotografia). Muzeul Na\u021bional Brukenthal - https://culturalia.ro/entities/67b766b9-c5d3-47ec-8286-2f7e734b45ca/view. CC BY-SA - http://creativecommons.org/licenses/by-sa/4.0/",
            "htmlAttributionSnippet": "<link rel='stylesheet' type='text/css' href='https://api.europeana.eu/attribution/style.css'/><dl class='europeana-attribution' lang='en'><dt>Creator</dt><dd lang=''>Editura Schwarze, Bra\u0219ov (\u0219i fotografia)</dd><dt>Institution</dt><dd lang=''><a href='https://culturalia.ro/entities/67b766b9-c5d3-47ec-8286-2f7e734b45ca/view' target='_blank' rel='noopener'>Muzeul Na\u021bional Brukenthal</a></dd><dt>Country</dt><dd lang=''>Romania</dd><dt>Rights</dt><dd><a href='http://creativecommons.org/licenses/by-sa/4.0/' target='_blank' rel='noopener'><span class='icon-cc'/><span class='icon-by'/><span class='icon-sa'/>CC BY-SA</a></dd></dl>",
            "ebucoreHasMimeType": "text/html",
            "ebucoreFileByteSize": 0
        },
        {
            "about": "https://resource.culturalia.ro/public/2000/01/01/_SB-BRUK-validat_08%20august%202020_istorie_georgescu_docpatv494/Imagini1/08E1F690CF6544E0B2017AA6FE8CFCEA.tif",
            "textAttributionSnippet": " - https://www.europeana.eu/item/951/Culturalia_67b766b9_c5d3_47ec_8286_2f7e734b45ca. Editura Schwarze, Bra\u0219ov (\u0219i fotografia). Muzeul Na\u021bional Brukenthal - https://culturalia.ro/entities/67b766b9-c5d3-47ec-8286-2f7e734b45ca/view. CC BY-SA - http://creativecommons.org/licenses/by-sa/4.0/",
            "htmlAttributionSnippet": "<link rel='stylesheet' type='text/css' href='https://api.europeana.eu/attribution/style.css'/><dl class='europeana-attribution' lang='en'><dt>Creator</dt><dd lang=''>Editura Schwarze, Bra\u0219ov (\u0219i fotografia)</dd><dt>Institution</dt><dd lang=''><a href='https://culturalia.ro/entities/67b766b9-c5d3-47ec-8286-2f7e734b45ca/view' target='_blank' rel='noopener'>Muzeul Na\u021bional Brukenthal</a></dd><dt>Country</dt><dd lang=''>Romania</dd><dt>Rights</dt><dd><a href='http://creativecommons.org/licenses/by-sa/4.0/' target='_blank' rel='noopener'><span class='icon-cc'/><span class='icon-by'/><span class='icon-sa'/>CC BY-SA</a></dd></dl>",
            "dctermsIsReferencedBy": [
                "https://iiif.europeana.eu/presentation/951/Culturalia_67b766b9_c5d3_47ec_8286_2f7e734b45ca/manifest"
            ],
            "ebucoreHasMimeType": "image/tiff",
            "ebucoreFileByteSize": 23074076,
            "ebucoreWidth": 3479,
            "ebucoreHeight": 2209,
            "edmHasColorSpace": "sRGB",
            "edmComponentColor": [
                "#CD853F",
                "#C0C0C0",
                "#FAF0E6",
                "#FFFAFA",
                "#FFE4C4",
                "#F5F5DC"
            ],
            "ebucoreOrientation": "landscape"
        },
        {
            "about": "https://resource.culturalia.ro/public/2000/01/01/_SB-BRUK-validat_08%20august%202020_istorie_georgescu_docpatv494/Imagini1/58063E8496A641C984132644A978A169.tif",
            "textAttributionSnippet": " - https://www.europeana.eu/item/951/Culturalia_67b766b9_c5d3_47ec_8286_2f7e734b45ca. Editura Schwarze, Bra\u0219ov (\u0219i fotografia). Muzeul Na\u021bional Brukenthal - https://culturalia.ro/entities/67b766b9-c5d3-47ec-8286-2f7e734b45ca/view. CC BY-SA - http://creativecommons.org/licenses/by-sa/4.0/",
            "htmlAttributionSnippet": "<link rel='stylesheet' type='text/css' href='https://api.europeana.eu/attribution/style.css'/><dl class='europeana-attribution' lang='en'><dt>Creator</dt><dd lang=''>Editura Schwarze, Bra\u0219ov (\u0219i fotografia)</dd><dt>Institution</dt><dd lang=''><a href='https://culturalia.ro/entities/67b766b9-c5d3-47ec-8286-2f7e734b45ca/view' target='_blank' rel='noopener'>Muzeul Na\u021bional Brukenthal</a></dd><dt>Country</dt><dd lang=''>Romania</dd><dt>Rights</dt><dd><a href='http://creativecommons.org/licenses/by-sa/4.0/' target='_blank' rel='noopener'><span class='icon-cc'/><span class='icon-by'/><span class='icon-sa'/>CC BY-SA</a></dd></dl>",
            "dctermsIsReferencedBy": [
                "https://iiif.europeana.eu/presentation/951/Culturalia_67b766b9_c5d3_47ec_8286_2f7e734b45ca/manifest"
            ],
            "ebucoreHasMimeType": "image/tiff",
            "ebucoreFileByteSize": 23074076,
            "ebucoreWidth": 3479,
            "ebucoreHeight": 2209,
            "edmHasColorSpace": "sRGB",
            "edmComponentColor": [
                "#708090",
                "#CD5C5C",
                "#E9967A",
                "#EEE8AA",
                "#FFFAFA",
                "#F5DEB3"
            ],
            "ebucoreOrientation": "landscape"
        },
        {
            "about": "https://iiif.europeana.eu/presentation/951/Culturalia_67b766b9_c5d3_47ec_8286_2f7e734b45ca/manifest",
            "rdfType": "http://iiif.io/api/presentation/3#Manifest"
        }
    ],
    "concept_label": [
        "Postcard"
    ],
    "concept_note": [
        "Type of postal stationery"
    ],
    "edmDatasetName": [
        "951_Ministerul_Culturii_Artifacts"
    ],
    "edmCountry": [
        "Romania"
    ],
    "edmLanguage": [
        "ro"
    ],
    "organization_label": [
        "National Heritage Institute, Bucharest"
    ],
    "coordinate": [
        [
            45.65,
            25.5833
        ],
        [
            46.0,
            25.0
        ],
        [
            45.0,
            22.0
        ],
        [
            46.0,
            25.0
        ]
    ]
}