{
    "aggregations_about": "/aggregation/provider/951/Culturalia_1fbbb1e2_6968_4a63_b5ce_e90523e393e1",
    "webResources": [
        {
            "about": "https://resource.culturalia.ro/public/2000/01/01/_SB-BRUK-validat_05%20Mai%202020_istorie_voina_docpatv494/Imagini1/C00678B271B441B6B4E4B6803719A2CD.tif",
            "textAttributionSnippet": " - https://www.europeana.eu/item/951/Culturalia_1fbbb1e2_6968_4a63_b5ce_e90523e393e1. Editura Emil Fischer. Muzeul Na\u021bional Brukenthal - https://culturalia.ro/entities/1fbbb1e2-6968-4a63-b5ce-e90523e393e1/view. CC BY-SA - http://creativecommons.org/licenses/by-sa/4.0/",
            "htmlAttributionSnippet": "<link rel='stylesheet' type='text/css' href='https://api.europeana.eu/attribution/style.css'/><dl class='europeana-attribution' lang='en'><dt>Creator</dt><dd lang=''>Editura Emil Fischer</dd><dt>Institution</dt><dd lang=''><a href='https://culturalia.ro/entities/1fbbb1e2-6968-4a63-b5ce-e90523e393e1/view' target='_blank' rel='noopener'>Muzeul Na\u021bional Brukenthal</a></dd><dt>Country</dt><dd lang=''>Romania</dd><dt>Rights</dt><dd><a href='http://creativecommons.org/licenses/by-sa/4.0/' target='_blank' rel='noopener'><span class='icon-cc'/><span class='icon-by'/><span class='icon-sa'/>CC BY-SA</a></dd></dl>",
            "dctermsIsReferencedBy": [
                "https://iiif.europeana.eu/presentation/951/Culturalia_1fbbb1e2_6968_4a63_b5ce_e90523e393e1/manifest"
            ],
            "ebucoreHasMimeType": "image/tiff",
            "ebucoreFileByteSize": 22590858,
            "ebucoreWidth": 3403,
            "ebucoreHeight": 2211,
            "edmHasColorSpace": "sRGB",
            "edmComponentColor": [
                "#F5F5DC",
                "#FFF8DC",
                "#FFEBCD",
                "#A9A9A9",
                "#FFEFD5",
                "#FFE4C4"
            ],
            "ebucoreOrientation": "landscape"
        },
        {
            "about": "https://culturalia.ro/entities/1fbbb1e2-6968-4a63-b5ce-e90523e393e1/view",
            "textAttributionSnippet": " - https://www.europeana.eu/item/951/Culturalia_1fbbb1e2_6968_4a63_b5ce_e90523e393e1. Editura Emil Fischer. Muzeul Na\u021bional Brukenthal - https://culturalia.ro/entities/1fbbb1e2-6968-4a63-b5ce-e90523e393e1/view. CC BY-SA - http://creativecommons.org/licenses/by-sa/4.0/",
            "htmlAttributionSnippet": "<link rel='stylesheet' type='text/css' href='https://api.europeana.eu/attribution/style.css'/><dl class='europeana-attribution' lang='en'><dt>Creator</dt><dd lang=''>Editura Emil Fischer</dd><dt>Institution</dt><dd lang=''><a href='https://culturalia.ro/entities/1fbbb1e2-6968-4a63-b5ce-e90523e393e1/view' target='_blank' rel='noopener'>Muzeul Na\u021bional Brukenthal</a></dd><dt>Country</dt><dd lang=''>Romania</dd><dt>Rights</dt><dd><a href='http://creativecommons.org/licenses/by-sa/4.0/' target='_blank' rel='noopener'><span class='icon-cc'/><span class='icon-by'/><span class='icon-sa'/>CC BY-SA</a></dd></dl>",
            "ebucoreHasMimeType": "text/html",
            "ebucoreFileByteSize": 0
        },
        {
            "about": "https://resource.culturalia.ro/public/2000/01/01/_SB-BRUK-validat_05%20Mai%202020_istorie_voina_docpatv494/Imagini1/94DE2F7E17DB4B09B8FE682E32F92789.tif",
            "textAttributionSnippet": " - https://www.europeana.eu/item/951/Culturalia_1fbbb1e2_6968_4a63_b5ce_e90523e393e1. Editura Emil Fischer. Muzeul Na\u021bional Brukenthal - https://culturalia.ro/entities/1fbbb1e2-6968-4a63-b5ce-e90523e393e1/view. CC BY-SA - http://creativecommons.org/licenses/by-sa/4.0/",
            "htmlAttributionSnippet": "<link rel='stylesheet' type='text/css' href='https://api.europeana.eu/attribution/style.css'/><dl class='europeana-attribution' lang='en'><dt>Creator</dt><dd lang=''>Editura Emil Fischer</dd><dt>Institution</dt><dd lang=''><a href='https://culturalia.ro/entities/1fbbb1e2-6968-4a63-b5ce-e90523e393e1/view' target='_blank' rel='noopener'>Muzeul Na\u021bional Brukenthal</a></dd><dt>Country</dt><dd lang=''>Romania</dd><dt>Rights</dt><dd><a href='http://creativecommons.org/licenses/by-sa/4.0/' target='_blank' rel='noopener'><span class='icon-cc'/><span class='icon-by'/><span class='icon-sa'/>CC BY-SA</a></dd></dl>",
            "dctermsIsReferencedBy": [
                "https://iiif.europeana.eu/presentation/951/Culturalia_1fbbb1e2_6968_4a63_b5ce_e90523e393e1/manifest"
            ],
            "ebucoreHasMimeType": "image/tiff",
            "ebucoreFileByteSize": 22893238,
            "ebucoreWidth": 3410,
            "ebucoreHeight": 2236,
            "edmHasColorSpace": "sRGB",
            "edmComponentColor": [
                "#BDB76B",
                "#808080",
                "#DCDCDC",
                "#C0C0C0",
                "#556B2F",
                "#FFE4C4"
            ],
            "ebucoreOrientation": "landscape"
        },
        {
            "about": "https://iiif.europeana.eu/presentation/951/Culturalia_1fbbb1e2_6968_4a63_b5ce_e90523e393e1/manifest",
            "rdfType": "http://iiif.io/api/presentation/3#Manifest"
        }
    ],
    "concept_label": [
        "history (discipline)"
    ],
    "concept_note": [
        "Discipline that studies the chronological record of events, such as affecting a nation, community, individual, object, or place, based on a critical examination of source materials and usually presenting an explanation of their causes."
    ],
    "edmDatasetName": [
        "951_Ministerul_Culturii_Artifacts"
    ],
    "edmCountry": [
        "Romania"
    ],
    "edmLanguage": [
        "ro"
    ],
    "organization_label": [
        "National Heritage Institute, Bucharest"
    ],
    "coordinate": [
        [
            46.0,
            25.0
        ],
        [
            45.87,
            24.23
        ],
        [
            45.0,
            22.0
        ],
        [
            46.0,
            25.0
        ],
        [
            45.7667,
            24.15
        ]
    ]
}